desman/__init__.py
desman/desman.py
desman-1.0.5.dist-info/LICENSE
desman-1.0.5.dist-info/METADATA
desman-1.0.5.dist-info/WHEEL
desman-1.0.5.dist-info/entry_points.txt
desman-1.0.5.dist-info/top_level.txt
desman-1.0.5.dist-info/RECORD
