Metadata-Version: 2.1
Name: desman
Version: 1.0.5
Summary: Console HTTP API tool
Home-page: https://github.com/kirillsulim/desman
Author: Kirill Sulim
Author-email: kirillsulim@gmail.com
License: UNKNOWN
Platform: UNKNOWN
Classifier: Development Status :: 4 - Beta
Classifier: Environment :: Console
Classifier: Intended Audience :: Developers
Classifier: Programming Language :: Python :: 3
Classifier: Programming Language :: Python :: 3.6
Classifier: License :: OSI Approved :: MIT License
Classifier: Topic :: Internet :: WWW/HTTP
Classifier: Operating System :: OS Independent
Requires-Dist: requests (>=2.19.1)
Requires-Dist: pyyaml (>=3.13)
Requires-Dist: Jinja2 (>=2.10)
